pilotpy/__init__.py
pilotpy/pl.py
pilotpy/plot/.ipynb_checkpoints/gene_selection_analysis-checkpoint.py
pilotpy/plot/__init__.py
pilotpy/plot/curve_activity.py
pilotpy/plot/gene_selection_analysis.py
pilotpy/plot/ploting.py
pilotpy/plot/pseudobulk_DE_analysis.py
pilotpy/tl.py
pilotpy/tools/.ipynb_checkpoints/__init__-checkpoint.py
pilotpy/tools/Cell_gene_selection.py
pilotpy/tools/Gene_cluster_specific.py
pilotpy/tools/Gene_cluster_specific_functions.py
pilotpy/tools/Trajectory.py
pilotpy/tools/__init__.py
pilotpy/tools/patients_sub_clustering.py
pilotpy-2.0.6.dist-info/LICENSE
pilotpy-2.0.6.dist-info/METADATA
pilotpy-2.0.6.dist-info/WHEEL
pilotpy-2.0.6.dist-info/RECORD
