Metadata-Version: 2.1
Name: pilotpy
Version: 2.0.6
Summary: PILOT: Detection of PatIent-Level distances from single cell genomics and pathomics data with Optimal Transport (PILOT)
License: MIT
Author: Mehdi Joodaki
Requires-Python: ==3.11.5
Classifier: License :: OSI Approved :: MIT License
Classifier: Programming Language :: Python :: 3
Requires-Dist: POT (>=0.9.1,<0.10.0)
Requires-Dist: adjustText (>=0.8,<0.9)
Requires-Dist: cycler (>=0.11.0,<0.12.0)
Requires-Dist: elpigraph-python (>=0.3.1,<0.4.0)
Requires-Dist: gprofiler-official (>=1.0.0,<2.0.0)
Requires-Dist: joypy (>=0.2.6,<0.3.0)
Requires-Dist: leidenalg (>=0.10.1,<0.11.0)
Requires-Dist: matplotlib (>=3.8.0,<4.0.0)
Requires-Dist: numpy (>=1.24.4,<2.0.0)
Requires-Dist: pandas (>=2.0.3,<3.0.0)
Requires-Dist: plotly (>=5.22.0,<6.0.0)
Requires-Dist: plotnine (>=0.12.3,<0.13.0)
Requires-Dist: pydiffmap (>=0.2.0.1,<0.3.0.0)
Requires-Dist: rpy2 (==3.5.11)
Requires-Dist: scanpy (>=1.9.5,<2.0.0)
Requires-Dist: scikit-learn (>=1.3.0,<2.0.0)
Requires-Dist: scikit-network (>=0.31.0,<0.32.0)
Requires-Dist: scipy (>=1.11.2,<2.0.0)
Requires-Dist: seaborn (>=0.12.2,<0.13.0)
Requires-Dist: shap (>=0.42.1,<0.43.0)
Requires-Dist: statsmodels (>=0.14.0,<0.15.0)
